falcon_vue/__init__.py
falcon_vue/core.py
falcon_vue/router.py
falcon_vue/util.py
falcon_vue-0.1.4.dist-info/METADATA
falcon_vue-0.1.4.dist-info/RECORD
falcon_vue-0.1.4.dist-info/WHEEL
falcon_vue-0.1.4.dist-info/top_level.txt
tests/__init__.py
tests/test_core.py
tests/test_router.py
tests/test_util.py
