Metadata-Version: 2.1
Name: falcon-vue
Version: 0.1.4
Summary: An unladen web framework for building APIs and app backends.
Home-page: https://github.com/shimakaze-git/falcon-vue
Author: shimakaze-git
Author-email: shimakaze.soft@gmail.com
License: MIT
Keywords: falcon vue falcon-vue falcon_vue
Platform: UNKNOWN
Classifier: Programming Language :: Python :: 3
Classifier: Programming Language :: Python :: 3.4
Classifier: License :: OSI Approved :: MIT License
Requires-Python: >=3.4, !=2.7.*
Requires-Dist: falcon (>=1.4.0)
